bert2tf/__init__.py
bert2tf/enums.py
bert2tf/excepts.py
bert2tf/helper.py
bert2tf/importer.py
bert2tf/baml/__init__.py
bert2tf/baml/helper.py
bert2tf/baml/parsers/__init__.py
bert2tf/baml/parsers/base.py
bert2tf/baml/parsers/driver/__init__.py
bert2tf/baml/parsers/driver/legacy.py
bert2tf/baml/parsers/executor/__init__.py
bert2tf/baml/parsers/executor/legacy.py
bert2tf/baml/parsers/flow/__init__.py
bert2tf/baml/parsers/flow/legacy.py
bert2tf/client/__init__.py
bert2tf/client/request.py
bert2tf/client/python/__init__.py
bert2tf/client/python/grpc.py
bert2tf/drivers/__init__.py
bert2tf/drivers/control.py
bert2tf/drivers/model.py
bert2tf/drivers/route.py
bert2tf/drivers/tokenizer.py
bert2tf/executors/__init__.py
bert2tf/executors/metas.py
bert2tf/executors/requests.py
bert2tf/executors/models/__init__.py
bert2tf/executors/models/auto_regressive.py
bert2tf/executors/models/configs.py
bert2tf/executors/models/embedding.py
bert2tf/executors/models/helper.py
bert2tf/executors/models/losses.py
bert2tf/executors/models/optimizers.py
bert2tf/executors/models/plugins.py
bert2tf/executors/models/bert/__init__.py
bert2tf/executors/models/electra/__init__.py
bert2tf/executors/models/gpt/__init__.py
bert2tf/executors/models/plm_bert/__init__.py
bert2tf/executors/models/roberta/__init__.py
bert2tf/executors/models/soft_masked_bert/__init__.py
bert2tf/executors/models/transformer/__init__.py
bert2tf/executors/tokenizers/__init__.py
bert2tf/executors/tokenizers/bert.py
bert2tf/executors/tokenizers/gpt.py
bert2tf/executors/tokenizers/helper.py
bert2tf/flow/__init__.py
bert2tf/logging/__init__.py
bert2tf/logging/base.py
bert2tf/logging/profile.py
bert2tf/parser/__init__.py
bert2tf/parser/helper.py
bert2tf/peapods/__init__.py
bert2tf/peapods/helper.py
bert2tf/peapods/zmq.py
bert2tf/peapods/pea/__init__.py
bert2tf/peapods/pea/head_pea.py
bert2tf/peapods/pea/helper.py
bert2tf/peapods/pea/tail_pea.py
bert2tf/peapods/pea/gateway/__init__.py
bert2tf/peapods/pea/gateway/grpc_asyncio.py
bert2tf-0.3.1.dist-info/LICENSE
bert2tf-0.3.1.dist-info/METADATA
bert2tf-0.3.1.dist-info/WHEEL
bert2tf-0.3.1.dist-info/top_level.txt
bert2tf-0.3.1.dist-info/RECORD
