Metadata-Version: 2.1
Name: bert2tf
Version: 0.3.1
Summary: ('A framework for user easy to load pre trained models with tensorflow keras, like bert gpt2 etc',)
Home-page: https://github.com/xiongma/bert2tf
Author: Xiong Ma
Author-email: cally.maxiong@gmail.com
Maintainer: Xiong Ma
Maintainer-email: cally.maxiong@gmail.com
License: Apache 2.1
Download-URL: https://github.com/xiongma/bert2tf/tags
Platform: linux
Platform: mac
Requires-Python: >=3.8.0
Requires-Dist: tensorflow-gpu
Requires-Dist: pyzmq
Requires-Dist: pyyaml
Requires-Dist: tornado
Requires-Dist: grpcio
Requires-Dist: uvloop
Requires-Dist: GPUtil
Requires-Dist: numpy
